stranslate/__init__.py
stranslate-1.0.9.dist-info/LICENSE
stranslate-1.0.9.dist-info/METADATA
stranslate-1.0.9.dist-info/WHEEL
stranslate-1.0.9.dist-info/top_level.txt
stranslate-1.0.9.dist-info/RECORD
