Metadata-Version: 2.1
Name: stranslate
Version: 1.0.9
Summary: A simple language translation module
Home-page: https://github.com/pypa/sampleproject
Author: Surya ST
Author-email: suryast566@gmail.com
License: UNKNOWN
Platform: UNKNOWN
Classifier: Programming Language :: Python :: 3
Classifier: License :: OSI Approved :: MIT License
Classifier: Operating System :: OS Independent
